whatsapp_formatter/__init__.py
whatsapp_formatter/formatter.py
whatsapp_formatter/parser.py
whatsapp_formatter/schemas.py
whatsapp_formatter/transformer.py
whatsapp_formatter/formatters/__init__.py
whatsapp_formatter/formatters/list_message.py
whatsapp_formatter/formatters/plain_text.py
whatsapp_formatter/formatters/quick_reply.py
whatsapp_formatter/utils/__init__.py
whatsapp_formatter/utils/deduplication.py
whatsapp_formatter/utils/truncation.py
whatsapp_formatter-0.2.0.dist-info/METADATA
whatsapp_formatter-0.2.0.dist-info/WHEEL
whatsapp_formatter-0.2.0.dist-info/licenses/LICENSE
whatsapp_formatter-0.2.0.dist-info/RECORD
