Metadata-Version: 2.4
Name: whatsapp-formatter
Version: 0.2.0
Summary: Transform LLM output to WhatsApp Business API JSON format
Project-URL: Homepage, https://github.com/dnivra26/whatsapp-formatter
Project-URL: Repository, https://github.com/dnivra26/whatsapp-formatter
Project-URL: Issues, https://github.com/dnivra26/whatsapp-formatter/issues
Author-email: Arvind Thangamani <dnivra26@gmail.com>
License-Expression: MIT
License-File: LICENSE
Keywords: chatbot,formatter,llm,messaging,whatsapp,whatsapp-api,whatsapp-business
Classifier: Development Status :: 4 - Beta
Classifier: Intended Audience :: Developers
Classifier: License :: OSI Approved :: MIT License
Classifier: Operating System :: OS Independent
Classifier: Programming Language :: Python :: 3
Classifier: Programming Language :: Python :: 3.10
Classifier: Programming Language :: Python :: 3.11
Classifier: Programming Language :: Python :: 3.12
Classifier: Programming Language :: Python :: 3.13
Classifier: Topic :: Communications :: Chat
Classifier: Topic :: Software Development :: Libraries :: Python Modules
Classifier: Typing :: Typed
Requires-Python: >=3.10
Requires-Dist: openai>=1.0.0
Requires-Dist: pydantic>=2.0.0
Provides-Extra: dev
Requires-Dist: build; extra == 'dev'
Requires-Dist: pytest>=8.0.0; extra == 'dev'
Requires-Dist: twine; extra == 'dev'
